nawalny/__init__.py
nawalny/nawalny_ps.py
nawalny/nawalny_rr.py
nawalny/examples/CommonServices_27.0.0.xsd
nawalny/examples/GeneralinformationServices_27.0.0.xsd
nawalny/examples/GeneralinformationServices_PREOPS_27.0.0.wsdl
nawalny/examples/howto04na_r01.py
nawalny/examples/nawalny_ps_demo.py
nawalny/examples/nawalny_rr_selftest.py
nawalny/examples/template.conf
nawalny-0.4.dist-info/METADATA
nawalny-0.4.dist-info/WHEEL
nawalny-0.4.dist-info/licenses/LICENSE
nawalny-0.4.dist-info/RECORD
