Metadata-Version: 2.4
Name: nawalny
Version: 0.4
Summary: A Python3 framework to access Eurocontrol NMB2B api properly
Project-URL: Homepage, https://github.com/DGAC/nawalny
Project-URL: Documentation, https://gitlab.asap.dsna.fr/didier.pavet/nmaka
Project-URL: Issues, https://github.com/DGAC/nawalny/issues
Author-email: Didier Pavet <dpa4aviation@gmail.com>
License-Expression: LGPL-2.1-or-later
License-File: LICENSE
Classifier: Development Status :: 3 - Alpha
Classifier: Intended Audience :: Developers
Classifier: Intended Audience :: Science/Research
Classifier: Operating System :: OS Independent
Classifier: Programming Language :: Python :: 3
Classifier: Topic :: Communications
Classifier: Topic :: Software Development :: Libraries :: Python Modules
Requires-Python: >=3.8
Requires-Dist: python-qpid-proton
Requires-Dist: requests
Requires-Dist: termcolor
Requires-Dist: zeep>4.1.0
